pytestifyx/__init__.py
pytestifyx/chinese_fix.py
pytestifyx/cli.py
pytestifyx/config.py
pytestifyx/core.py
pytestifyx/parse.py
pytestifyx/scaffold.py
pytestifyx/driver/__init__.py
pytestifyx/driver/api.py
pytestifyx/driver/web.py
pytestifyx/utils/__init__.py
pytestifyx/utils/data_factory/__init__.py
pytestifyx/utils/data_factory/run.py
pytestifyx/utils/data_factory/core/__init__.py
pytestifyx/utils/data_factory/core/config.py
pytestifyx/utils/data_factory/core/factory.py
pytestifyx/utils/data_factory/core/generator.py
pytestifyx/utils/data_factory/core/loading.py
pytestifyx/utils/data_factory/providers/__init__.py
pytestifyx/utils/data_factory/providers/basic/__init__.py
pytestifyx/utils/data_factory/providers/name/__init__.py
pytestifyx/utils/data_factory/providers/ssn/__init__.py
pytestifyx/utils/data_factory/single_interface/__init__.py
pytestifyx/utils/data_factory/single_interface/common_field.py
pytestifyx/utils/data_factory/single_interface/strategy.py
pytestifyx/utils/database/__init__.py
pytestifyx/utils/database/case.py
pytestifyx/utils/database/assertion/__init__.py
pytestifyx/utils/database/assertion/core.py
pytestifyx/utils/database/model/__init__.py
pytestifyx/utils/database/model/core.py
pytestifyx/utils/decorator/__init__.py
pytestifyx/utils/decorator/database.py
pytestifyx/utils/decorator/login.py
pytestifyx/utils/decorator/public.py
pytestifyx/utils/dubbo/__init__.py
pytestifyx/utils/dubbo/core.py
pytestifyx/utils/json/__init__.py
pytestifyx/utils/json/core.py
pytestifyx/utils/json/utils.py
pytestifyx/utils/logs/__init__.py
pytestifyx/utils/logs/config.py
pytestifyx/utils/logs/core.py
pytestifyx/utils/logs/monkey_print.py
pytestifyx/utils/msg_push/__init__.py
pytestifyx/utils/msg_push/email_tools.py
pytestifyx/utils/msg_push/feishu_tools.py
pytestifyx/utils/parse/__init__.py
pytestifyx/utils/parse/config.py
pytestifyx/utils/parse/xmind_parse.py
pytestifyx/utils/public/__init__.py
pytestifyx/utils/public/constant.py
pytestifyx-0.10.0.dist-info/METADATA
pytestifyx-0.10.0.dist-info/WHEEL
pytestifyx-0.10.0.dist-info/entry_points.txt
pytestifyx-0.10.0.dist-info/licenses/LICENSE
pytestifyx-0.10.0.dist-info/RECORD
