Metadata-Version: 2.4
Name: pytestifyx
Version: 0.10.0
Summary: pytestifyx is a pytest-based automation testing framework for api, ui, app testing
Project-URL: Homepage, https://github.com/jaylu2018/PyTestifyx
Project-URL: Repository, https://github.com/jaylu2018/PyTestifyx
Author-email: luyh <jaylu1995@outlook.com>
License: Apache License 2.0
License-File: LICENSE
Keywords: api,app,automation,pytest,testing,ui
Classifier: Intended Audience :: Developers
Classifier: Operating System :: MacOS :: MacOS X
Classifier: Operating System :: Microsoft :: Windows
Classifier: Programming Language :: Python
Classifier: Programming Language :: Python :: 3.13
Requires-Python: >=3.13
Requires-Dist: deepdiff>=8.6.1
Requires-Dist: loguru>=0.7.3
Requires-Dist: playwright>=1.57.0
Requires-Dist: prettytable>=3.17.0
Requires-Dist: pytest-cases>=3.9.1
Requires-Dist: pytest-playwright>=0.7.2
Requires-Dist: pytest>=9.0.2
Requires-Dist: pyyaml>=6.0.1
Requires-Dist: requests-toolbelt==1.0.0
Requires-Dist: requests==2.29.0
Requires-Dist: xmindparser>=1.0.9
